<cdidata>
  <cdi type="zip">
    <location name="73007">
      <cdi>2</cdi>
      <nresp>1</nresp>
      <dist>9</dist>
      <lat>35.685166984</lat>
      <lon>-97.3241441</lon>
      <name>Arcadia</name>
      <state>OK</state>
    </location>
    <location name="73013">
      <cdi>2.6912</cdi>
      <nresp>4</nresp>
      <dist>10</dist>
      <lat>35.6220704839</lat>
      <lon>-97.4858455914</lon>
      <name>Edmond</name>
      <state>OK</state>
    </location>
    <location name="73034">
      <cdi>3.4579</cdi>
      <nresp>8</nresp>
      <dist>7</dist>
      <lat>35.7023169435</lat>
      <lon>-97.4284925058</lon>
      <name>Edmond</name>
      <state>OK</state>
    </location>
    <location name="73044">
      <cdi>2.2372</cdi>
      <nresp>1</nresp>
      <dist>21</dist>
      <lat>35.8555874545</lat>
      <lon>-97.4533252066</lon>
      <name>Guthrie</name>
      <state>OK</state>
    </location>
    <location name="74023">
      <cdi>2</cdi>
      <nresp>1</nresp>
      <dist>70</dist>
      <lat>35.9970321702</lat>
      <lon>-96.737107477</lon>
      <name>Cushing</name>
      <state>OK</state>
    </location>
  </cdi>
</cdidata>
