<cdidata>
  <cdi type="zip">
    <location name="75038">
      <cdi>2</cdi>
      <nresp>1</nresp>
      <dist>7</dist>
      <lat>32.8722318141</lat>
      <lon>-96.9804105835</lon>
      <name>Irving</name>
      <state>TX</state>
    </location>
    <location name="75062">
      <cdi>2.0027</cdi>
      <nresp>3</nresp>
      <dist>5</dist>
      <lat>32.8466187025</lat>
      <lon>-96.9592247696</lon>
      <name>Irving</name>
      <state>TX</state>
    </location>
    <location name="75063">
      <cdi>1</cdi>
      <nresp>1</nresp>
      <dist>11</dist>
      <lat>32.9206335879</lat>
      <lon>-96.9754663768</lon>
      <name>Irving</name>
      <state>TX</state>
    </location>
    <location name="75231">
      <cdi>2</cdi>
      <nresp>1</nresp>
      <dist>18</dist>
      <lat>32.8775682201</lat>
      <lon>-96.7498121491</lon>
      <name>Dallas</name>
      <state>TX</state>
    </location>
  </cdi>
</cdidata>
