<cdidata>
  <cdi type="zip">
    <location name="67037">
      <cdi>2.2372</cdi>
      <nresp>1</nresp>
      <dist>156</dist>
      <lat>37.5637110992</lat>
      <lon>-97.2213664898</lon>
      <name>Derby</name>
      <state>KS</state>
    </location>
    <location name="73072">
      <cdi>1</cdi>
      <nresp>1</nresp>
      <dist>114</dist>
      <lat>35.2154624134</lat>
      <lon>-97.4942440373</lon>
      <name>Norman</name>
      <state>OK</state>
    </location>
    <location name="73162">
      <cdi>1</cdi>
      <nresp>1</nresp>
      <dist>87</dist>
      <lat>35.5808656078</lat>
      <lon>-97.6415225426</lon>
      <name>Oklahoma City</name>
      <state>OK</state>
    </location>
    <location name="74023">
      <cdi>2</cdi>
      <nresp>1</nresp>
      <dist>29</dist>
      <lat>35.9970321702</lat>
      <lon>-96.737107477</lon>
      <name>Cushing</name>
      <state>OK</state>
    </location>
    <location name="74074">
      <cdi>3.1473</cdi>
      <nresp>14</nresp>
      <dist>14</dist>
      <lat>36.0759277283</lat>
      <lon>-97.0995974939</lon>
      <name>Stillwater</name>
      <state>OK</state>
    </location>
    <location name="74075">
      <cdi>3.5096</cdi>
      <nresp>19</nresp>
      <dist>7</dist>
      <lat>36.175402583</lat>
      <lon>-97.0633810292</lon>
      <name>Stillwater</name>
      <state>OK</state>
    </location>
    <location name="74077">
      <cdi>3.2754</cdi>
      <nresp>2</nresp>
      <dist>9</dist>
      <lat>36.1228033078</lat>
      <lon>-97.0706479473</lon>
      <name>Stillwater</name>
      <state>OK</state>
    </location>
    <location name="74078">
      <cdi>3.0916</cdi>
      <nresp>1</nresp>
      <dist>9</dist>
      <lat>36.1268891113</lat>
      <lon>-97.0810412844</lon>
      <name>Stillwater</name>
      <state>OK</state>
    </location>
  </cdi>
</cdidata>
